<?xml version="1.0" encoding="UTF-8"?>
<!DOCTYPE tiles-definitions PUBLIC
       "-//Apache Software Foundation//DTD Tiles Configuration 3.0//EN"
       "http://tiles.apache.org/dtds/tiles-config_3_0.dtd">
<tiles-definitions>
	<!-- member 관련 작업으로 response될 페이지를 등록하는 설정파일 -->
	<definition name="loginTemplate" template="/WEB-INF/member/login.jsp">
	</definition>
	<definition name="signTemplate" template="/WEB-INF/member/sign.jsp">
	</definition>
	<definition name="find_id" template="/WEB-INF/member/find_id.jsp">
	</definition>
	<definition name="find_id_page" template="/WEB-INF/member/find_id_page.jsp">
	</definition>
	<definition name="find_pass" template="/WEB-INF/member/find_pass.jsp">
	</definition>
	<definition name="find_pass_page" template="/WEB-INF/member/find_pass_page.jsp">
	</definition>
	<definition name="loginok"  extends = "mainTemplate">
	<put-attribute name="content" value="/WEB-INF/layout/index.jsp"/>
	</definition>
</tiles-definitions> 